{"type": "object"
,"required": ["cur_id", "config", "delete", "actions"]
,"properties":
    {"cur_id": {"type": "integer"}
    ,"config":
        {"type": "object"
        ,"properties": {"min_version": {"type": "integer"}}
        }
    ,"delete": {"type": "object"}
    ,"actions":
        {"type": "object"
        ,"required":
            ["minimize", "go_prev", "go_next", "go_next_unrated"
            ,"go_prev_unrated", "go_start", "go_end", "reload", "save"
            ,"show_tracks", "focus_album_search", "focus_id_search"
            ,"focus_track_search", "delete_tracks"
            ]
        ,"properties":
            {"minimize":
                {"type": "object"
                ,"properties":
                    {"hotkeys": {"type": "array"}
                    ,"hint": {"type": "string"}
                    }
                }
            ,"go_prev":
                {"type": "object"
                ,"properties":
                    {"hotkeys": {"type": "array"}
                    ,"hint": {"type": "string"}
                    }
                }
            ,"go_next":
                {"type": "object"
                ,"properties":
                    {"hotkeys": {"type": "array"}
                    ,"hint": {"type": "string"}
                    }
                }
            ,"go_next_unrated":
                {"type": "object"
                ,"properties":
                    {"hotkeys": {"type": "array"}
                    ,"hint": {"type": "string"}
                    }
                }
            ,"go_prev_unrated":
                {"type": "object"
                ,"properties":
                    {"hotkeys": {"type": "array"}
                    ,"hint": {"type": "string"}
                    }
                }
            ,"go_start":
                {"type": "object"
                ,"properties":
                    {"hotkeys": {"type": "array"}
                    ,"hint": {"type": "string"}
                    }
                }
            ,"go_end":
                {"type": "object"
                ,"properties":
                    {"hotkeys": {"type": "array"}
                    ,"hint": {"type": "string"}
                    }
                }
            ,"reload":
                {"type": "object"
                ,"properties":
                    {"hotkeys": {"type": "array"}
                    ,"hint": {"type": "string"}
                    }
                }
            ,"save":
                {"type": "object"
                ,"properties":
                    {"hotkeys": {"type": "array"}
                    ,"hint": {"type": "string"}
                    }
                }
            ,"show_tracks":
                {"type": "object"
                ,"properties":
                    {"hotkeys": {"type": "array"}
                    ,"hint": {"type": "string"}
                    }
                }
            ,"focus_album_search":
                {"type": "object"
                ,"properties":
                    {"hotkeys": {"type": "array"}
                    ,"hint": {"type": "string"}
                    }
                }
            ,"focus_id_search":
                {"type": "object"
                ,"properties":
                    {"hotkeys": {"type": "array"}
                    ,"hint": {"type": "string"}
                    }
                }
            ,"focus_track_search":
                {"type": "object"
                ,"properties":
                    {"hotkeys": {"type": "array"}
                    ,"hint": {"type": "string"}
                    }
                }
            ,"delete_tracks":
                {"type": "object"
                ,"properties":
                    {"hotkeys": {"type": "array"}
                    ,"hint": {"type": "string"}
                    }
                }
            }
        }
    }
}
